remarkable_keyboard/__init__.py
remarkable_keyboard/mappings.py
remarkable_keyboard/remarkable_keyboard.py
remarkable_keyboard/version.py
remarkable_keyboard-4.0.1.dist-info/LICENSE
remarkable_keyboard-4.0.1.dist-info/METADATA
remarkable_keyboard-4.0.1.dist-info/WHEEL
remarkable_keyboard-4.0.1.dist-info/entry_points.txt
remarkable_keyboard-4.0.1.dist-info/top_level.txt
remarkable_keyboard-4.0.1.dist-info/RECORD
