Metadata-Version: 2.1
Name: remarkable-keyboard
Version: 4.0.1
Summary: use reMarkable as a wireless mouse and keyboard
Home-page: https://github.com/evidlo/remarkable_keyboard
Author: Evan Widloski
Author-email: evan@evanw.org
License: GPLv3
Keywords: remarkable tablet evdev mouse keyboard
Classifier: Programming Language :: Python :: 3
License-File: LICENSE
Requires-Dist: pycryptodome
Requires-Dist: paramiko
Requires-Dist: screeninfo
Requires-Dist: pynput
Requires-Dist: remarkable-mouse (>=5)
Requires-Dist: sortedcontainers
